baseblock/__init__.py
baseblock/base_object.py
baseblock/common_utils.py
baseblock/crypto_base.py
baseblock/enforce_type.py
baseblock/env_io.py
baseblock/file_io.py
baseblock/service_event_generator.py
baseblock/stopwatch.py
baseblock/text_matcher.py
baseblock/text_utils.py
baseblock/time_helper.py
baseblock-0.2.24.dist-info/METADATA
baseblock-0.2.24.dist-info/WHEEL
baseblock-0.2.24.dist-info/RECORD
